sfcli-0.1.8.1.dist-info/METADATA
sfcli-0.1.8.1.dist-info/RECORD
sfcli-0.1.8.1.dist-info/WHEEL
sfcli-0.1.8.1.dist-info/entry_points.txt
sfcli-0.1.8.1.dist-info/top_level.txt
tech/__init__.py
tech/mlsql/__init__.py
tech/mlsql/serviceframework/__init__.py
tech/mlsql/serviceframework/version.py
tech/mlsql/serviceframework/scripts/__init__.py
tech/mlsql/serviceframework/scripts/actionmanager.py
tech/mlsql/serviceframework/scripts/appruntime.py
tech/mlsql/serviceframework/scripts/jarmanager.py
tech/mlsql/serviceframework/scripts/pathmanager.py
tech/mlsql/serviceframework/scripts/process_info.py
tech/mlsql/serviceframework/scripts/processutils.py
tech/mlsql/serviceframework/scripts/projectmanager.py
tech/mlsql/serviceframework/scripts/scripts.py
tech/mlsql/serviceframework/scripts/shellutils.py
tech/mlsql/serviceframework/scripts/test.py
